epoch_protos/__init__.py
epoch_protos/chart_def_pb2.py
epoch_protos/chart_def_pb2.pyi
epoch_protos/common_pb2.py
epoch_protos/common_pb2.pyi
epoch_protos/table_def_pb2.py
epoch_protos/table_def_pb2.pyi
epoch_protos/tearsheet_pb2.py
epoch_protos/tearsheet_pb2.pyi
epoch_protos-2.0.9.dist-info/METADATA
epoch_protos-2.0.9.dist-info/WHEEL
epoch_protos-2.0.9.dist-info/top_level.txt
epoch_protos-2.0.9.dist-info/RECORD
